[  
  {"title":"Atemosta Home", "description":"Welcome to the Tempest.", "url":"https://atemosta.com/"},  
  {"title":"Monument of Life (Immria)", "description":"Engrave your name into the metaverse with NFTs", "url": "https://immria.atemosta.com/monument-of-life/index.html"},
  {"title":"Myujen", "description":"Buy and Sell 3D NFTs via the Polygon Network.", "url": "https://atemosta.com/projects/myujen/"},
  {"title":"Tolbana", "description":"Buy and sell physical goods anonymously with cryptocurrency.", "url": "https://atemosta.com/projects/tolbana/"}
]  
